tarte/__init__.py
tarte/splitter.py
tarte/tagger.py
tarte/trainer.py
tarte/cli/__init__.py
tarte/cli/convert.py
tarte/cli/dataset.py
tarte/cli/group.py
tarte/cli/test.py
tarte/cli/train.py
tarte/modules/__init__.py
tarte/modules/base.py
tarte/modules/classifier.py
tarte/modules/embeddings.py
tarte/modules/encoder.py
tarte/modules/models.py
tarte/modules/scorer.py
tarte/utils/__init__.py
tarte/utils/constants.py
tarte/utils/datasets.py
tarte/utils/labels.py
tarte/utils/reader.py
nlp_tarte-0.0.1.dist-info/METADATA
nlp_tarte-0.0.1.dist-info/WHEEL
nlp_tarte-0.0.1.dist-info/entry_points.txt
nlp_tarte-0.0.1.dist-info/top_level.txt
nlp_tarte-0.0.1.dist-info/RECORD
