Metadata-Version: 2.1
Name: nlp-tarte
Version: 0.0.1
Summary: A framework for disambiguation
Home-page: https://github.com/ponteineptique/tarte
Author: Thibault Clérice
License: MIT
Platform: UNKNOWN
Classifier: License :: OSI Approved :: MIT License
Classifier: Programming Language :: Python
Classifier: Programming Language :: Python :: 3
Classifier: Programming Language :: Python :: 3.6
Classifier: Programming Language :: Python :: Implementation :: CPython
Classifier: Programming Language :: Python :: Implementation :: PyPy
Classifier: Topic :: Text Processing :: Linguistic
Requires-Python: >=3.6.0
Requires-Dist: nlp-pie (<=1.0.0,>=0.2.2)
Requires-Dist: regex
